{
  "print-to-pdf-bottom-margin": 1.0, 
  "print-to-pdf-right-margin": 1.0, 
  "viewer_toc_isvisible": false, 
  "multiplier": 1.8000001907348633, 
  "print-to-pdf-page-numbers": true, 
  "viewer_window_geometry": {
    "__class__": "bytearray", 
    "__value__": "AdnQywACAAAAAAAAAAAAKQAACf8AAAWfAAAAAQAAACkAAAn+AAAFngAAAAAAAAAACgA="
  }, 
  "viewer_splitter_state": {
    "__class__": "bytearray", 
    "__value__": "AAAA/wAAAAAAAAACAAAAlgAAASwAAAAABgEAAAAB"
  }, 
  "print-to-pdf-page-size": "a4", 
  "custom_colors_for_color_dialog": [
    [
      255, 
      255, 
      255, 
      255
    ], 
    [
      255, 
      255, 
      255, 
      255
    ], 
    [
      255, 
      255, 
      255, 
      255
    ], 
    [
      255, 
      255, 
      255, 
      255
    ], 
    [
      255, 
      255, 
      255, 
      255
    ], 
    [
      255, 
      255, 
      255, 
      255
    ], 
    [
      255, 
      255, 
      255, 
      255
    ], 
    [
      255, 
      255, 
      255, 
      255
    ], 
    [
      255, 
      255, 
      255, 
      255
    ], 
    [
      255, 
      255, 
      255, 
      255
    ], 
    [
      255, 
      255, 
      255, 
      255
    ], 
    [
      255, 
      255, 
      255, 
      255
    ], 
    [
      255, 
      255, 
      255, 
      255
    ], 
    [
      255, 
      255, 
      255, 
      255
    ], 
    [
      255, 
      255, 
      255, 
      255
    ], 
    [
      255, 
      255, 
      255, 
      255
    ]
  ], 
  "viewer_open_history": [
    "/tmp/mozilla_dnc0/Varlam Shalamov-Kolyma Tales (Classic, 20th-Century, Penguin)-Penguin Classics (1995).epub", 
    "/tmp/mozilla_dnc0/S.N.U.F.F_ - Victor Pelevin.epub", 
    "/tmp/mozilla_dnc0/(Inspector Sejer 5) Karin Fossum-Black Seconds-Random House (2008).epub", 
    "/tmp/mozilla_dnc0/S.N.U.F.F_ - Victor Pelevin-1.epub", 
    "/home/dnc/Calibre Library/Jeff Marsden/THE CATCHER IN THE RYE (67)/THE CATCHER IN THE RYE - Jeff Marsden.azw3", 
    "/home/dnc/Calibre Library/Victor Pelevin/S.N.U.F.F_ (66)/S.N.U.F.F_ - Victor Pelevin.epub", 
    "/home/dnc/Calibre Library/Victor Pelevin/S.N.U.F.F_ (66)/S.N.U.F.F_ - Victor Pelevin.azw3", 
    "/tmp/mozilla_dnc0/Norton, Graham-The Life and Loves of a He Devil.A Memoir-Hodder & Stoughton (2014).epub", 
    "/tmp/mozilla_dnc0/(Schocken Classics Series) Franz Kafka-Diaries, 1910-1923-Schocken (1988).epub", 
    "/tmp/mozilla_dnc0/(Yale Nota Bene) Bloom, Harold_ O'Neill, Eugene-Long day's journey into night-Yale University Press (2001).epub", 
    "/tmp/mozilla_dnc0/Grant_S._Ingersoll,_Thomas_S._Morton,_Andrew_L._Farris_Taming_Text_How_to_Find,_Organize,_and_Manipulate_It.epub", 
    "/home/dnc/downloads/Keith_Richards_Life.epub", 
    "/home/dnc/downloads/Ivo_Andri\u0107,_William_H._McNeil_The_Bridge_on_the_Drina.mobi", 
    "/home/dnc/downloads/George_Saunders_Lincoln_in_The_Bardo_A_Novel.epub", 
    "/home/dnc/downloads/John_Truby_The_Anatomy_of_Story_22_Steps_to_Becoming_a_Master_Storyteller.epub", 
    "/home/dnc/Calibre Library/Ron Hansen/You've Got to Read This_ Contemporary American Writers Introduce Stories That Held Them in Awe (57)/You've Got to Read This_ Contemporary Amer - Ron Hansen.epub", 
    "/home/dnc/Calibre Library/Nathalie Babel, Peter Constantine Isaac Babel/The Complete Works of Isaac Babel Reprint Edition by Isaac Babel, Nathalie Babel, Peter Constant (56)/The Complete Works of Isaac Babel Reprint - Nathalie Babel, Peter Constantine Isaac Ba.epub", 
    "/tmp/mozilla_dnc0/Isaac_Babel,_Nathalie_Babel,_Peter_Constantine,_Cynthia_Ozick_The_Complete_Works_of_Isaac_Babel.epub", 
    "/tmp/mozilla_dnc0/Tao_Lin_Shoplifting_from_American_Apparel.mobi", 
    "/tmp/mozilla_dnc0/Maupassant,_Guy_de;_Maupassant,_Guy_de;_Coward,_David_A_day_in_the_country_and_other_stories.epub", 
    "/tmp/mozilla_dnc0/Ron_Hansen_Youve_Got_to_Read_This_Contemporary_American_Writers_Introduce_Stories_that_Held_Them_in_Awe__.epub", 
    "/tmp/mozilla_dnc0/Francis Scott Fitzgerald-This Side of Paradise-Publishing in Motion (2011).epub", 
    "/tmp/mozilla_dnc0/Carlo Rovelli-Reality Is Not What It Seems_ The Journey to Quantum Gravity-Penguin UK (2016).epub", 
    "/tmp/mozilla_dnc0/(Hardcover Classics) Rainer Maria Rilke, Charlie Louth, Lewis Hyde-Letters to a Young Poet-Penguin Classics (2013).epub", 
    "/tmp/mozilla_dnc0/David_Lynch_Catching_the_Big_Fish_Meditation,_Consciousness,_and_Creativity.epub", 
    "/tmp/mozilla_dnc0/John_Yates_Culadasa,_with_J._Graves,_M._Immergut_The_Mind_Illuminated__A_Complete_Meditation_Guide_Integrating_Buddhist_Wisdom_and_Brain_Science.epub", 
    "/tmp/mozilla_dnc0/Arthur_Rimbaud,_Wyatt_Mason_I_Promise_to_Be_Good_The_Letters_of_Arthur_Rimbaud.epub", 
    "/media/dnc/Kindle/documents/The Magic Mountain - Thomas Mann.azw3", 
    "/tmp/mozilla_dnc0/Victor_Pelevin,_Andrew_Bromfield_Homo_Zapiens.epub", 
    "/home/dnc/downloads/Cormac_McCarthy_Blood_Meridian_Or_the_Evening_Redness_in_the_West__\u00a0.epub", 
    "/tmp/mozilla_dnc0/Fyodor_Dostoevsky,_Constance_Garnett_Brothers_Karamazov.epub", 
    "/tmp/mozilla_dnc0/(Everyman's library 145) Josipovici, Gabriel_ Kafka, Franz-Collected stories-Knopf Doubleday Publishing Group_Everyman's Library_Distributed by Random House, Knopf (1993).epub", 
    "/tmp/mozilla_dnc0/Franz+Kafka+-+La+metamorfosis.mobi", 
    "/tmp/mozilla_dnc0/pg5200.mobi", 
    "/tmp/mozilla_dnc0/pg5200-images.mobi", 
    "/tmp/mozilla_dnc0/pg5200-images.epub", 
    "/tmp/mozilla_dnc0/Bob_Dylan_Chronicles,_Volume_1.mobi", 
    "/tmp/mozilla_dnc0/Anton_Chekhov_Stories_of_Anton_Chekhov.epub", 
    "/tmp/mozilla_dnc0/Anton_Chekhov_Collected_Stories.epub", 
    "/tmp/mozilla_dnc0/Kurt_Vonnegut_Slaughterhouse-Five_A_Novel.epub", 
    "/tmp/mozilla_dnc0/[Roberto_Bolano]_2666_A_Novel(BookFi).epub", 
    "/tmp/mozilla_dnc0/Haruki Murakami-What I Talk About When I Talk About Running-Knopf Doubleday Publishing Group (2008).epub", 
    "/home/dnc/Calibre Library/Murakami, Haruki/1Q84 (19)/1Q84 - Murakami, Haruki.epub", 
    "/tmp/mozilla_dnc0/Haruki_Murakami_1Q84__.epub", 
    "/home/dnc/.cache/.fr-nfmg77/book_06335.epub", 
    "/home/dnc/downloads/Karl_Ove_Knausgaard_My_Struggle_Book_Four.epub", 
    "/home/dnc/Calibre Library/C.G. Jung/Memories, Dreams, Reflections (7)/Memories, Dreams, Reflections - C.G. Jung.epub", 
    "/home/dnc/Calibre Library/Too Fat to Fish/Artie Lange (5)/Artie Lange - Too Fat to Fish.epub", 
    "/tmp/mozilla_dnc0/propp.mobi", 
    "/home/dnc/Calibre Library/Maggie Nelson/The Argonauts (2)/The Argonauts - Maggie Nelson.epub"
  ], 
  "viewer_toolbar_state": {
    "__class__": "bytearray", 
    "__value__": "AAAA/wAAAAH9AAAAAAAABRsAAAK0AAAABAAAAAQAAAAIAAAACPwAAAACAAAAAAAAAAEAAAAQAHQAbwBvAGwAXwBiAGEAcgMAAAAA/////wAAAAAAAAAAAAAAAgAAAAEAAAASAHQAbwBvAGwAXwBiAGEAcgAyAQAAAAD/////AAAAAAAAAAA="
  }, 
  "print-to-pdf-geometry": {
    "__class__": "bytearray", 
    "__value__": "AdnQywACAAAAAAd6AAABVAAAChAAAANxAAAHfAAAAVQAAAoOAAADbwAAAAAAAAAACgA="
  }, 
  "print-to-pdf-top-margin": 1.0, 
  "print-to-pdf-left-margin": 1.0, 
  "main_window_state": {
    "__class__": "bytearray", 
    "__value__": "AAAA/wAAAAL9AAAAAwAAAAAAAAAAAAAAAPwCAAAAAfsAAAAQAHQAbwBjAC0AZABvAGMAawAAAAAA/////wAAAMwA////AAAAAQAAAAAAAAAA/AIAAAAB+wAAABwAYgBvAG8AawBtAGEAcgBrAHMALQBkAG8AYwBrAAAAAAD/////AAABOQD///8AAAADAAAAAAAAAAD8AQAAAAH7AAAAHABmAG8AbwB0AG4AbwB0AGUAcwAtAGQAbwBjAGsAAAAAAP////8AAABPAP///wAACbwAAAU2AAAAAQAAAAIAAAABAAAAAvwAAAACAAAAAAAAAAEAAAAQAHQAbwBvAGwAXwBiAGEAcgMAAAAA/////wAAAAAAAAAAAAAAAgAAAAEAAAASAHQAbwBvAGwAXwBiAGEAcgAyAQAAAAD/////AAAAAAAAAAA="
  }, 
  "in_paged_mode": true, 
  "print-to-pdf-show-file": true
}